CarDEC_CITE/CarDEC_CITE_API.py
CarDEC_CITE/CarDEC_CITE_MainModel.py
CarDEC_CITE/CarDEC_CITE_SAE.py
CarDEC_CITE/CarDEC_CITE_count_decoder.py
CarDEC_CITE/CarDEC_CITE_dataloaders.py
CarDEC_CITE/CarDEC_CITE_layers.py
CarDEC_CITE/CarDEC_CITE_optimization.py
CarDEC_CITE/CarDEC_CITE_utils.py
CarDEC_CITE/__init__.py
cardec_cite-1.1.0.dist-info/LICENSE.rtf
cardec_cite-1.1.0.dist-info/METADATA
cardec_cite-1.1.0.dist-info/WHEEL
cardec_cite-1.1.0.dist-info/top_level.txt
cardec_cite-1.1.0.dist-info/RECORD
