Metadata-Version: 2.1
Name: cardec-cite
Version: 1.1.0
Summary: A deep learning method for joint batch correction, denoting, and clustering of cite-seq data.
Home-page: https://github.com/HanyingYan/CarDEC_CITE
Author: Hanying Yan
Author-email: hanying.yan16@gmail.com
Classifier: Programming Language :: Python :: 3
Classifier: License :: OSI Approved :: MIT License
Classifier: Operating System :: OS Independent
Requires-Python: >=3.7
License-File: LICENSE.rtf
Requires-Dist: numpy (>=1.18.1)
Requires-Dist: pandas (>=1.0.1)
Requires-Dist: scipy (>=1.4.1)
Requires-Dist: tensorflow (<=2.3.1,>=2.0.1)
Requires-Dist: scikit-learn (>=0.22.2.post1)
Requires-Dist: scanpy (>=1.5.1)
Requires-Dist: louvain (>=0.6.1)
